mne_vision/__init__.py
mne_vision/__main__.py
mne_vision/main_controller.py
mne_vision/main_listener.py
mne_vision/main_model.py
mne_vision/main_view.py
mne_vision/classification/__init__.py
mne_vision/classification/applePy/__init__.py
mne_vision/classification/applePy/channel_selection.py
mne_vision/classification/applePy/channel_selection_without_covariances.py
mne_vision/classification/applePy/classifier.py
mne_vision/classification/applePy/cnn.py
mne_vision/classification/applePy/pipeline_catalogue.py
mne_vision/classification/applePy/saver.py
mne_vision/classification/applePy/sources_estimator.py
mne_vision/classification/applePy/tools.py
mne_vision/classification/applePy/transformer.py
mne_vision/classification/classify/__init__.py
mne_vision/classification/classify/classify_controller.py
mne_vision/classification/classify/classify_listener.py
mne_vision/classification/classify/classify_view.py
mne_vision/connectivity/__init__.py
mne_vision/connectivity/envelope_correlation/__init__.py
mne_vision/connectivity/envelope_correlation/envelope_correlation_controller.py
mne_vision/connectivity/envelope_correlation/envelope_correlation_listener.py
mne_vision/connectivity/envelope_correlation/envelope_correlation_view.py
mne_vision/connectivity/sensor_space_connectivity/__init__.py
mne_vision/connectivity/sensor_space_connectivity/sensor_space_connectivity_controller.py
mne_vision/connectivity/sensor_space_connectivity/sensor_space_connectivity_listener.py
mne_vision/connectivity/sensor_space_connectivity/sensor_space_connectivity_view.py
mne_vision/connectivity/source_space_connectivity/__init__.py
mne_vision/connectivity/source_space_connectivity/source_space_connectivity_controller.py
mne_vision/connectivity/source_space_connectivity/source_space_connectivity_listener.py
mne_vision/connectivity/source_space_connectivity/source_space_connectivity_view.py
mne_vision/connectivity/spectro_temporal_connectivity/__init__.py
mne_vision-0.1.1.dist-info/LICENSE
mne_vision-0.1.1.dist-info/METADATA
mne_vision-0.1.1.dist-info/WHEEL
mne_vision-0.1.1.dist-info/entry_points.txt
mne_vision-0.1.1.dist-info/top_level.txt
mne_vision-0.1.1.dist-info/RECORD
