Metadata-Version: 2.1
Name: mne-vision
Version: 0.1.1
Summary: MNE Vision is a GUI for MNE
Home-page: https://github.com/alemahie/MNE_Vision
Author: Lemahieu Antoine
Author-email: Antoine.Lemahieu@ulb.be
Project-URL: Bug Tracker, https://github.com/alemahie/MNE_Vision/issues
Keywords: EEG,MNE,GUI
Classifier: Programming Language :: Python :: 3
Classifier: License :: OSI Approved :: GNU General Public License v3 (GPLv3)
Classifier: Operating System :: OS Independent
Requires-Python: >=3.6
License-File: LICENSE
Requires-Dist: eeglabio (>=0.0.1.post7)
Requires-Dist: keras (>=2.9.0)
Requires-Dist: matplotlib (>=3.5.2)
Requires-Dist: mne (>=1.0.3)
Requires-Dist: mne-connectivity (>=0.3)
Requires-Dist: numpy (>=1.22.4)
Requires-Dist: pymatreader (>=0.0.30)
Requires-Dist: PyQt5 (>=5.15.6)
Requires-Dist: PyQt5-stubs (>=5.15.6.0)
Requires-Dist: pyriemann (>=0.2.7)
Requires-Dist: pyvista (>=0.34.1)
Requires-Dist: pyvistaqt (>=0.9.0)
Requires-Dist: scikit-learn (>=1.1.1)
Requires-Dist: scipy (>=1.8.1)
Requires-Dist: seaborn (>=0.11.2)
Requires-Dist: tensorflow (>=2.9.1)
